README.rst
setup.py
borda/__init__.py
borda/client.py
borda/count.py
borda/server.py
borda/tests.py
borda.egg-info/PKG-INFO
borda.egg-info/SOURCES.txt
borda.egg-info/dependency_links.txt
borda.egg-info/entry_points.txt
borda.egg-info/requires.txt
borda.egg-info/top_level.txt
borda.egg-info/zip-safe