Metadata-Version: 1.1
Name: borda
Version: 0.1
Summary: Voting system based on the Borda counting scheme
Home-page: https://github.com/logc/borda
Author: Luis Osa
Author-email: luis.osa.gdc@gmail.com
License: UNKNOWN
Platform: UNKNOWN
Classifier: Development Status :: 3 - Alpha
Classifier: Framework :: Bottle
Classifier: License :: OSI Approved :: GNU General Public License v3 (GPLv3)
Classifier: Topic :: Office/Business :: Groupware
